weather_harvester/__init__.py
weather_harvester/alerts.py
weather_harvester/cache.py
weather_harvester/cli.py
weather_harvester/config.py
weather_harvester/exporter.py
weather_harvester/fetcher.py
weather_harvester/logging_system.py
weather_harvester/main.py
weather_harvester/map_utils.py
weather_harvester/turtle_alert.py
weather_harvester-0.1.3.dist-info/METADATA
weather_harvester-0.1.3.dist-info/WHEEL
weather_harvester-0.1.3.dist-info/entry_points.txt
weather_harvester-0.1.3.dist-info/top_level.txt
weather_harvester-0.1.3.dist-info/RECORD
