Metadata-Version: 2.4
Name: weather_harvester
Version: 0.1.3
Summary: Weather Data Harvester with caching, alerts, CLI, and exports
Author: Your Name
Requires-Dist: colorama
Dynamic: author
Dynamic: requires-dist
Dynamic: summary
